geosd/__init__.py
geosd/common.py
geosd/geosd.py
geosd-0.0.1.dist-info/LICENSE
geosd-0.0.1.dist-info/METADATA
geosd-0.0.1.dist-info/WHEEL
geosd-0.0.1.dist-info/entry_points.txt
geosd-0.0.1.dist-info/top_level.txt
geosd-0.0.1.dist-info/RECORD
